[
    {
        "key": "sb",
        "value": "Vvi4Zghl5gsZFoP2cD11WLrN",
        "domain": "facebook.com",
        "path": "/",
        "hostOnly": false,
        "creation": "2025-04-17T10:18:42.314Z",
        "lastAccessed": "2025-04-17T10:18:42.314Z"
    },
    {
        "key": "ps_l",
        "value": "1",
        "domain": "facebook.com",
        "path": "/",
        "hostOnly": false,
        "creation": "2025-04-17T10:18:42.314Z",
        "lastAccessed": "2025-04-17T10:18:42.314Z"
    },
    {
        "key": "ps_n",
        "value": "1",
        "domain": "facebook.com",
        "path": "/",
        "hostOnly": false,
        "creation": "2025-04-17T10:18:42.314Z",
        "lastAccessed": "2025-04-17T10:18:42.314Z"
    },
    {
        "key": "datr",
        "value": "9dQAaAtMy7mDrYqwrqZlr-Wk",
        "domain": "facebook.com",
        "path": "/",
        "hostOnly": false,
        "creation": "2025-04-17T10:18:42.314Z",
        "lastAccessed": "2025-04-17T10:18:42.314Z"
    },
    {
        "key": "locale",
        "value": "en_US",
        "domain": "facebook.com",
        "path": "/",
        "hostOnly": false,
        "creation": "2025-04-17T10:18:42.314Z",
        "lastAccessed": "2025-04-17T10:18:42.314Z"
    },
    {
        "key": "c_user",
        "value": "61556531843531",
        "domain": "facebook.com",
        "path": "/",
        "hostOnly": false,
        "creation": "2025-04-17T10:18:42.314Z",
        "lastAccessed": "2025-04-17T10:18:42.314Z"
    },
    {
        "key": "xs",
        "value": "41%3Arm1GiyRSpypitQ%3A2%3A1744885031%3A-1%3A5483%3A%3AAcUiuJAZlklHAqd9ad34xx9tKgNTY6IzQL7sL7jwqg",
        "domain": "facebook.com",
        "path": "/",
        "hostOnly": false,
        "creation": "2025-04-17T10:18:42.314Z",
        "lastAccessed": "2025-04-17T10:18:42.314Z"
    },
    {
        "key": "wd",
        "value": "1920x945",
        "domain": "facebook.com",
        "path": "/",
        "hostOnly": false,
        "creation": "2025-04-17T10:18:42.314Z",
        "lastAccessed": "2025-04-17T10:18:42.314Z"
    },
    {
        "key": "fr",
        "value": "1TbNVtXs608GxVvv9.AWd7xJWN2PDypn5vMbC8gIOS1bid3DI57tcpjAeDuAqNgjR9Fs8.BoANVf..AAA.0.0.BoANWY.AWegVm56mf91lYbAymRLnT7chv0",
        "domain": "facebook.com",
        "path": "/",
        "hostOnly": false,
        "creation": "2025-04-17T10:18:42.314Z",
        "lastAccessed": "2025-04-17T10:18:42.314Z"
    }
]